{"results":[{"created_at":"Fri Nov 10 04:49:23 +0000 2017","id":928847027336646656,"id_str":"928847027336646656","text":"@pubkugyo \u307e\u305f\u7701\u7565\u3055\u308c\u3066\u307e\u3059\u306d\uff0e\u3053\u308c\uff0cTwitter\u306fAPI\u3092\u3061\u3083\u3093\u3068\u63d0\u4f9b\u3057\u3066\u3044\u308b\u306e\u3067\uff0c\u5404\u7a2e\u30b5\u30fc\u30f4\u30a3\u30b9\u304c\u4f7f\u3063\u3066\u308b\u30e9\u30a4\u30d6\u30e9\u30ea\u304c\u5bfe\u5fdc\u3057\u3066\u304f\u308c\u308b\u306e\u3092\u5f85\u3064\u304b\uff0c\u79c1\u304c\u4f5c\u308b\u3057\u304b\u306a\u3044\uff0e\u305f\u3068\u3048\u3070Ruby Gem\u306e\u5834\u5408\u306f\u3053\u3046\u3044\u3046PR\u304c\u51fa\u3066\u308b\nhttps:\/\/t.co\/5ei30Efome","display_text_range":[10,139],"source":"\u003ca href=\"http:\/\/itunes.apple.com\/us\/app\/twitter\/id409789998?mt=12\" rel=\"nofollow\"\u003eTwitter for Mac\u003c\/a\u003e","truncated":false,"in_reply_to_status_id":928419034294468608,"in_reply_to_status_id_str":"928419034294468608","in_reply_to_user_id":15861296,"in_reply_to_user_id_str":"15861296","in_reply_to_screen_name":"pubkugyo","user":{"id":281645570,"id_str":"281645570","name":"K WATANABE","screen_name":"hackugyo","location":null,"url":"http:\/\/d.hatena.ne.jp\/hackugyo","description":"2017\u5e74\u5ea6\u306f\u6a5f\u68b0\u5b66\u7fd2\u306b\u95a2\u5fc3\u3092\u5b9a\u3081\u305f\u65e5\u672c\u306e\u6280\u8853\u8005(7\u5e74\u3081)\uff0e\u30ea\u30ea\u30fc\u30b9\u7d4c\u9a13\u8a00\u8a9e\u306fRuby\u306e\u307b\u304bJava, Obj-C, C#, CS(AngularJS), Swift, Kotlin\uff0e\u30a8\u30c7\u30a3\u30bf\u306fEmacs. Ruby\u6280\u8853\u8005Silver\u30fb\u30b7\u30b9\u30c6\u30e0\u30a2\u30fc\u30ad\u30c6\u30af\u30c8 https:\/\/t.co\/GYwIkewx17","translator_type":"none","protected":false,"verified":false,"followers_count":249,"friends_count":622,"listed_count":15,"favourites_count":246,"statuses_count":806,"created_at":"Wed Apr 13 17:48:26 +0000 2011","utc_offset":32400,"time_zone":"Tokyo","geo_enabled":false,"lang":"ja","contributors_enabled":false,"is_translator":false,"profile_background_color":"000000","profile_background_image_url":"http:\/\/abs.twimg.com\/images\/themes\/theme1\/bg.png","profile_background_image_url_https":"https:\/\/abs.twimg.com\/images\/themes\/theme1\/bg.png","profile_background_tile":false,"profile_link_color":"F58EA8","profile_sidebar_border_color":"000000","profile_sidebar_fill_color":"000000","profile_text_color":"000000","profile_use_background_image":false,"profile_image_url":"http:\/\/pbs.twimg.com\/profile_images\/1310410213\/beholder_aprilfools_normal.png","profile_image_url_https":"https:\/\/pbs.twimg.com\/profile_images\/1310410213\/beholder_aprilfools_normal.png","default_profile":false,"default_profile_image":false,"following":null,"follow_request_sent":null,"notifications":null},"geo":null,"coordinates":null,"place":null,"contributors":null,"is_quote_status":false,"quote_count":0,"reply_count":0,"retweet_count":0,"favorite_count":0,"entities":{"hashtags":[],"urls":[{"url":"https:\/\/t.co\/5ei30Efome","expanded_url":"https:\/\/github.com\/sferik\/twitter\/pull\/864\/commits","display_url":"github.com\/sferik\/twitter\u2026","indices":[116,139]}],"user_mentions":[{"screen_name":"pubkugyo","name":"kugyo W","id":15861296,"id_str":"15861296","indices":[0,9]}],"symbols":[]},"favorited":false,"retweeted":false,"possibly_sensitive":false,"filter_level":"low","lang":"ja","matching_rules":[{"tag":null}]},{"created_at":"Wed Nov 08 23:29:28 +0000 2017","id":928404132498612225,"id_str":"928404132498612225","text":"https:\/\/t.co\/boYhvxkd4F","source":"\u003ca href=\"http:\/\/itunes.apple.com\/us\/app\/twitter\/id409789998?mt=12\" rel=\"nofollow\"\u003eTwitter for Mac\u003c\/a\u003e","truncated":false,"in_reply_to_status_id":null,"in_reply_to_status_id_str":null,"in_reply_to_user_id":null,"in_reply_to_user_id_str":null,"in_reply_to_screen_name":null,"user":{"id":213747670,"id_str":"213747670","name":"The Ruby Gem","screen_name":"gem","location":null,"url":null,"description":null,"translator_type":"none","protected":false,"verified":false,"followers_count":1722,"friends_count":10,"listed_count":128,"favourites_count":335,"statuses_count":120,"created_at":"Tue Nov 09 18:03:22 +0000 2010","utc_offset":-28800,"time_zone":"Pacific Time (US & Canada)","geo_enabled":true,"lang":"en","contributors_enabled":false,"is_translator":false,"profile_background_color":"C0DEED","profile_background_image_url":"http:\/\/abs.twimg.com\/images\/themes\/theme1\/bg.png","profile_background_image_url_https":"https:\/\/abs.twimg.com\/images\/themes\/theme1\/bg.png","profile_background_tile":false,"profile_link_color":"1DA1F2","profile_sidebar_border_color":"C0DEED","profile_sidebar_fill_color":"DDEEF6","profile_text_color":"333333","profile_use_background_image":true,"profile_image_url":"http:\/\/pbs.twimg.com\/profile_images\/531994916181012480\/EBap51cO_normal.png","profile_image_url_https":"https:\/\/pbs.twimg.com\/profile_images\/531994916181012480\/EBap51cO_normal.png","default_profile":true,"default_profile_image":false,"following":null,"follow_request_sent":null,"notifications":null},"geo":null,"coordinates":null,"place":null,"contributors":null,"is_quote_status":false,"quote_count":0,"reply_count":0,"retweet_count":0,"favorite_count":0,"entities":{"hashtags":[],"urls":[{"url":"https:\/\/t.co\/boYhvxkd4F","expanded_url":"https:\/\/github.com\/sferik\/twitter\/commit\/2912a67c7ec5b733ddd01531b91a9ff5fd3b3012","display_url":"github.com\/sferik\/twitter\u2026","indices":[0,23]}],"user_mentions":[],"symbols":[]},"favorited":false,"retweeted":false,"possibly_sensitive":false,"filter_level":"low","lang":"und","matching_rules":[{"tag":null}]},{"created_at":"Mon Nov 06 08:08:05 +0000 2017","id":927447480832212992,"id_str":"927447480832212992","text":"Twitter gem \u306e\nhttps:\/\/t.co\/5BkXTAgLDi\nhttps:\/\/t.co\/vPre4iQluw\n\u3053\u306e\u8fba\u308a\u306e\u4f8b\u5916\u3069\u3046\u634c\u304f\u304b\u306a\u30fc\u3002","source":"\u003ca href=\"https:\/\/mobile.twitter.com\" rel=\"nofollow\"\u003eTwitter Lite\u003c\/a\u003e","truncated":false,"in_reply_to_status_id":null,"in_reply_to_status_id_str":null,"in_reply_to_user_id":null,"in_reply_to_user_id_str":null,"in_reply_to_screen_name":null,"user":{"id":193008438,"id_str":"193008438","name":"\u51fa\u529b\u30bc\u30ed","screen_name":"s_of_p","location":"OVER THE ATMOSPHERE","url":"http:\/\/0xbd.cf","description":"\u308f\u305f\u3057\u305f\u3061\u306f\u547d\u3092\u501f\u308a\u3066\u611b\u306e\u306a\u304b\u306b\u751f\u304d\u3066\u3044\u308b","translator_type":"none","protected":false,"verified":false,"followers_count":267,"friends_count":2177,"listed_count":16,"favourites_count":8008,"statuses_count":8191,"created_at":"Mon Sep 20 18:59:08 +0000 2010","utc_offset":32400,"time_zone":"Tokyo","geo_enabled":false,"lang":"en","contributors_enabled":false,"is_translator":false,"profile_background_color":"C5CAE9","profile_background_image_url":"http:\/\/abs.twimg.com\/images\/themes\/theme14\/bg.gif","profile_background_image_url_https":"https:\/\/abs.twimg.com\/images\/themes\/theme14\/bg.gif","profile_background_tile":false,"profile_link_color":"3F51B5","profile_sidebar_border_color":"000000","profile_sidebar_fill_color":"000000","profile_text_color":"000000","profile_use_background_image":false,"profile_image_url":"http:\/\/pbs.twimg.com\/profile_images\/2212542813\/ico_normal.PNG","profile_image_url_https":"https:\/\/pbs.twimg.com\/profile_images\/2212542813\/ico_normal.PNG","profile_banner_url":"https:\/\/pbs.twimg.com\/profile_banners\/193008438\/1487096821","default_profile":false,"default_profile_image":false,"following":null,"follow_request_sent":null,"notifications":null},"geo":null,"coordinates":null,"place":null,"contributors":null,"is_quote_status":false,"quote_count":0,"reply_count":0,"retweet_count":0,"favorite_count":0,"entities":{"hashtags":[],"urls":[{"url":"https:\/\/t.co\/5BkXTAgLDi","expanded_url":"https:\/\/github.com\/sferik\/twitter\/issues\/401","display_url":"github.com\/sferik\/twitter\u2026","indices":[14,37]},{"url":"https:\/\/t.co\/vPre4iQluw","expanded_url":"https:\/\/github.com\/sferik\/twitter\/issues\/535","display_url":"github.com\/sferik\/twitter\u2026","indices":[38,61]}],"user_mentions":[],"symbols":[]},"favorited":false,"retweeted":false,"possibly_sensitive":false,"filter_level":"low","lang":"ja","matching_rules":[{"tag":null}]},{"created_at":"Wed Oct 25 08:46:12 +0000 2017","id":923108418931507202,"id_str":"923108418931507202","text":"\u306a\u308b\u307b\u3069 \/ \u201cPlease expose id_str, in_reply_to_id_str etc by stve \u00b7 Pull Request #380 \u00b7 sferik\/twitter \u00b7 GitHub\u201d https:\/\/t.co\/vBuM4GRbae","source":"\u003ca href=\"http:\/\/www.hatena.ne.jp\/guide\/twitter\" rel=\"nofollow\"\u003eHatena\u003c\/a\u003e","truncated":false,"in_reply_to_status_id":null,"in_reply_to_status_id_str":null,"in_reply_to_user_id":null,"in_reply_to_user_id_str":null,"in_reply_to_screen_name":null,"user":{"id":303846231,"id_str":"303846231","name":"\u30ad\u30af\u30ca\u30f3\u30c8\u30ab","screen_name":"kikunantoka","location":null,"url":"https:\/\/kikunantoka.com","description":"\u6771\u4eac\u3067Web\u958b\u767a\u3057\u3066\u307e\u3059_(:3\u300d\u2220)_","translator_type":"none","protected":false,"verified":false,"followers_count":283,"friends_count":261,"listed_count":7,"favourites_count":3199,"statuses_count":6269,"created_at":"Mon May 23 14:28:36 +0000 2011","utc_offset":32400,"time_zone":"Tokyo","geo_enabled":true,"lang":"ja","contributors_enabled":false,"is_translator":false,"profile_background_color":"C0DEED","profile_background_image_url":"http:\/\/abs.twimg.com\/images\/themes\/theme1\/bg.png","profile_background_image_url_https":"https:\/\/abs.twimg.com\/images\/themes\/theme1\/bg.png","profile_background_tile":false,"profile_link_color":"1DA1F2","profile_sidebar_border_color":"C0DEED","profile_sidebar_fill_color":"DDEEF6","profile_text_color":"333333","profile_use_background_image":true,"profile_image_url":"http:\/\/pbs.twimg.com\/profile_images\/378800000738355373\/e0dc5694d9810df16cf62c7529098942_normal.jpeg","profile_image_url_https":"https:\/\/pbs.twimg.com\/profile_images\/378800000738355373\/e0dc5694d9810df16cf62c7529098942_normal.jpeg","profile_banner_url":"https:\/\/pbs.twimg.com\/profile_banners\/303846231\/1415541363","default_profile":true,"default_profile_image":false,"following":null,"follow_request_sent":null,"notifications":null},"geo":null,"coordinates":null,"place":null,"contributors":null,"is_quote_status":false,"quote_count":0,"reply_count":0,"retweet_count":0,"favorite_count":0,"entities":{"hashtags":[],"urls":[{"url":"https:\/\/t.co\/vBuM4GRbae","expanded_url":"http:\/\/htn.to\/M1FDoBhr","display_url":"htn.to\/M1FDoBhr","indices":[108,131]}],"user_mentions":[],"symbols":[]},"favorited":false,"retweeted":false,"possibly_sensitive":false,"filter_level":"low","lang":"ja","matching_rules":[{"tag":null}]}],"requestParameters":{"maxResults":100,"fromDate":"201710210000","toDate":"201711201720"}}